{"0":false,"nav_menu_locations":{"main_menu_home":12,"main_menu":13},"custom_css_post_id":-1,"custom_header":"32","top_bar_repeater_social":[],"menu_button_colors":{"link":"","hover":"","text":"","bg":"","border":""},"menu_button_colors_hover":{"link":"","hover":"","text":"","bg":"","border":""},"main_typography":{"font-family":"Raleway","font-size":"15px","variant":"regular","line-height":"1.6","letter-spacing":"0px","font-backup":"","font-weight":400,"font-style":"normal","downloadFont":true},"main_typography_titles":{"font-family":"","font-backup":"","variant":"","font-weight":0,"font-style":""}}